AUTHORS
COPYING
COPYRIGHT
ChangeLog
MANIFEST.in
README.rst
setup.py
python/RestAuthCommon/__init__.py
python/RestAuthCommon/error.py
python/RestAuthCommon/handlers.py
python/RestAuthCommon/strprep.py
python/RestAuthCommon.egg-info/PKG-INFO
python/RestAuthCommon.egg-info/SOURCES.txt
python/RestAuthCommon.egg-info/dependency_links.txt
python/RestAuthCommon.egg-info/top_level.txt